[
  {
    "id": "LF-1100",
    "contractId": "C-9000",
    "category": "Underbilling",
    "description": "Underbilling identified for contract 9000.",
    "impactUSD": 14574,
    "severity": "low"
  },
  {
    "id": "LF-1101",
    "contractId": "C-9001",
    "category": "Missing Indexation",
    "description": "Missing Indexation identified for contract 9001.",
    "impactUSD": 11808,
    "severity": "medium"
  },
  {
    "id": "LF-1102",
    "contractId": "C-9002",
    "category": "Unapproved Discounts",
    "description": "Unapproved Discounts identified for contract 9002.",
    "impactUSD": 25574,
    "severity": "high"
  },
  {
    "id": "LF-1103",
    "contractId": "C-9003",
    "category": "Late Fees Waived",
    "description": "Late Fees Waived identified for contract 9003.",
    "impactUSD": 2047,
    "severity": "low"
  },
  {
    "id": "LF-1104",
    "contractId": "C-9004",
    "category": "Renewal Missed",
    "description": "Renewal Missed identified for contract 9004.",
    "impactUSD": 12349,
    "severity": "medium"
  },
  {
    "id": "LF-1105",
    "contractId": "C-9005",
    "category": "Underbilling",
    "description": "Underbilling identified for contract 9005.",
    "impactUSD": 18523,
    "severity": "high"
  },
  {
    "id": "LF-1106",
    "contractId": "C-9006",
    "category": "Missing Indexation",
    "description": "Missing Indexation identified for contract 9006.",
    "impactUSD": 8134,
    "severity": "low"
  },
  {
    "id": "LF-1107",
    "contractId": "C-9007",
    "category": "Unapproved Discounts",
    "description": "Unapproved Discounts identified for contract 9007.",
    "impactUSD": 21862,
    "severity": "medium"
  },
  {
    "id": "LF-1108",
    "contractId": "C-9008",
    "category": "Late Fees Waived",
    "description": "Late Fees Waived identified for contract 9008.",
    "impactUSD": 19547,
    "severity": "high"
  },
  {
    "id": "LF-1109",
    "contractId": "C-9009",
    "category": "Renewal Missed",
    "description": "Renewal Missed identified for contract 9009.",
    "impactUSD": 6413,
    "severity": "low"
  },
  {
    "id": "LF-1110",
    "contractId": "C-9010",
    "category": "Underbilling",
    "description": "Underbilling identified for contract 9010.",
    "impactUSD": 18109,
    "severity": "medium"
  },
  {
    "id": "LF-1111",
    "contractId": "C-9011",
    "category": "Missing Indexation",
    "description": "Missing Indexation identified for contract 9011.",
    "impactUSD": 26226,
    "severity": "high"
  },
  {
    "id": "LF-1112",
    "contractId": "C-9012",
    "category": "Unapproved Discounts",
    "description": "Unapproved Discounts identified for contract 9012.",
    "impactUSD": 19736,
    "severity": "low"
  },
  {
    "id": "LF-1113",
    "contractId": "C-9013",
    "category": "Late Fees Waived",
    "description": "Late Fees Waived identified for contract 9013.",
    "impactUSD": 7784,
    "severity": "medium"
  },
  {
    "id": "LF-1114",
    "contractId": "C-9014",
    "category": "Renewal Missed",
    "description": "Renewal Missed identified for contract 9014.",
    "impactUSD": 21981,
    "severity": "high"
  },
  {
    "id": "LF-1115",
    "contractId": "C-9015",
    "category": "Underbilling",
    "description": "Underbilling identified for contract 9015.",
    "impactUSD": 5936,
    "severity": "low"
  },
  {
    "id": "LF-1116",
    "contractId": "C-9016",
    "category": "Missing Indexation",
    "description": "Missing Indexation identified for contract 9016.",
    "impactUSD": 3426,
    "severity": "medium"
  },
  {
    "id": "LF-1117",
    "contractId": "C-9017",
    "category": "Unapproved Discounts",
    "description": "Unapproved Discounts identified for contract 9017.",
    "impactUSD": 19882,
    "severity": "high"
  },
  {
    "id": "LF-1118",
    "contractId": "C-9018",
    "category": "Late Fees Waived",
    "description": "Late Fees Waived identified for contract 9018.",
    "impactUSD": 18971,
    "severity": "low"
  },
  {
    "id": "LF-1119",
    "contractId": "C-9019",
    "category": "Renewal Missed",
    "description": "Renewal Missed identified for contract 9019.",
    "impactUSD": 2178,
    "severity": "medium"
  },
  {
    "id": "LF-1120",
    "contractId": "C-9020",
    "category": "Underbilling",
    "description": "Underbilling identified for contract 9020.",
    "impactUSD": 19006,
    "severity": "high"
  },
  {
    "id": "LF-1121",
    "contractId": "C-9021",
    "category": "Missing Indexation",
    "description": "Missing Indexation identified for contract 9021.",
    "impactUSD": 13620,
    "severity": "low"
  },
  {
    "id": "LF-1122",
    "contractId": "C-9022",
    "category": "Unapproved Discounts",
    "description": "Unapproved Discounts identified for contract 9022.",
    "impactUSD": 24355,
    "severity": "medium"
  },
  {
    "id": "LF-1123",
    "contractId": "C-9023",
    "category": "Late Fees Waived",
    "description": "Late Fees Waived identified for contract 9023.",
    "impactUSD": 16600,
    "severity": "high"
  }
]