[
  {
    "id": "QT-1001",
    "opportunityId": "OPP-1001",
    "quoteNumber": "Q-1001",
    "owner": "Priya Patel",
    "amount": 28573.900726147836,
    "status": "Approved",
    "createdAt": "2024-02-11T00:00:00.000Z"
  },
  {
    "id": "QT-1002",
    "opportunityId": "OPP-1002",
    "quoteNumber": "Q-1002",
    "owner": "Alex Morgan",
    "amount": 85695.5291802022,
    "status": "Approved",
    "createdAt": "2024-03-18T00:00:00.000Z"
  },
  {
    "id": "QT-1003",
    "opportunityId": "OPP-1003",
    "quoteNumber": "Q-1003",
    "owner": "Priya Patel",
    "amount": 80316.28494772714,
    "status": "Approved",
    "createdAt": "2024-02-29T00:00:00.000Z"
  },
  {
    "id": "QT-1004",
    "opportunityId": "OPP-1004",
    "quoteNumber": "Q-1004",
    "owner": "Sofia Gomez",
    "amount": 59358.277382606895,
    "status": "Approved",
    "createdAt": "2024-06-20T00:00:00.000Z"
  },
  {
    "id": "QT-1005",
    "opportunityId": "OPP-1005",
    "quoteNumber": "Q-1005",
    "owner": "Priya Patel",
    "amount": 18812.642337710266,
    "status": "Approved",
    "createdAt": "2024-07-01T00:00:00.000Z"
  },
  {
    "id": "QT-1006",
    "opportunityId": "OPP-1006",
    "quoteNumber": "Q-1006",
    "owner": "Priya Patel",
    "amount": 51516.619022885905,
    "status": "Approved",
    "createdAt": "2024-11-01T00:00:00.000Z"
  },
  {
    "id": "QT-1007",
    "opportunityId": "OPP-1007",
    "quoteNumber": "Q-1007",
    "owner": "Alex Morgan",
    "amount": 67932.33028644447,
    "status": "Approved",
    "createdAt": "2024-04-24T00:00:00.000Z"
  },
  {
    "id": "QT-1008",
    "opportunityId": "OPP-1008",
    "quoteNumber": "Q-1008",
    "owner": "Liam Chen",
    "amount": 93260.9866895629,
    "status": "Approved",
    "createdAt": "2024-04-24T00:00:00.000Z"
  },
  {
    "id": "QT-1009",
    "opportunityId": "OPP-1009",
    "quoteNumber": "Q-1009",
    "owner": "Alex Morgan",
    "amount": 65592.86391704144,
    "status": "Approved",
    "createdAt": "2024-08-22T00:00:00.000Z"
  },
  {
    "id": "QT-1010",
    "opportunityId": "OPP-1010",
    "quoteNumber": "Q-1010",
    "owner": "Priya Patel",
    "amount": 56199.863865598905,
    "status": "Approved",
    "createdAt": "2024-05-08T00:00:00.000Z"
  },
  {
    "id": "QT-1011",
    "opportunityId": "OPP-1011",
    "quoteNumber": "Q-1011",
    "owner": "Priya Patel",
    "amount": 85626.554915031,
    "status": "Approved",
    "createdAt": "2024-05-16T00:00:00.000Z"
  },
  {
    "id": "QT-1012",
    "opportunityId": "OPP-1012",
    "quoteNumber": "Q-1012",
    "owner": "Alex Morgan",
    "amount": 96456.9502306701,
    "status": "Approved",
    "createdAt": "2024-09-19T00:00:00.000Z"
  },
  {
    "id": "QT-1013",
    "opportunityId": "OPP-1013",
    "quoteNumber": "Q-1013",
    "owner": "Liam Chen",
    "amount": 59237.932142017344,
    "status": "Approved",
    "createdAt": "2024-04-06T00:00:00.000Z"
  },
  {
    "id": "QT-1014",
    "opportunityId": "OPP-1014",
    "quoteNumber": "Q-1014",
    "owner": "Sofia Gomez",
    "amount": 70464.86577073565,
    "status": "Approved",
    "createdAt": "2024-05-22T00:00:00.000Z"
  },
  {
    "id": "QT-1015",
    "opportunityId": "OPP-1015",
    "quoteNumber": "Q-1015",
    "owner": "Jordan Smith",
    "amount": 55192.205173156406,
    "status": "Approved",
    "createdAt": "2024-12-21T00:00:00.000Z"
  },
  {
    "id": "QT-1016",
    "opportunityId": "OPP-1016",
    "quoteNumber": "Q-1016",
    "owner": "Jordan Smith",
    "amount": 85355.41607398112,
    "status": "Approved",
    "createdAt": "2024-02-07T00:00:00.000Z"
  },
  {
    "id": "QT-1017",
    "opportunityId": "OPP-1017",
    "quoteNumber": "Q-1017",
    "owner": "Liam Chen",
    "amount": 86368.96605963721,
    "status": "Approved",
    "createdAt": "2024-09-09T00:00:00.000Z"
  },
  {
    "id": "QT-1018",
    "opportunityId": "OPP-1018",
    "quoteNumber": "Q-1018",
    "owner": "Liam Chen",
    "amount": 91101.90263209109,
    "status": "Approved",
    "createdAt": "2024-05-16T00:00:00.000Z"
  },
  {
    "id": "QT-1019",
    "opportunityId": "OPP-1019",
    "quoteNumber": "Q-1019",
    "owner": "Sofia Gomez",
    "amount": 81117.5268285,
    "status": "Approved",
    "createdAt": "2024-04-10T00:00:00.000Z"
  },
  {
    "id": "QT-1020",
    "opportunityId": "OPP-1020",
    "quoteNumber": "Q-1020",
    "owner": "Sofia Gomez",
    "amount": 94139.96425030283,
    "status": "Approved",
    "createdAt": "2024-05-25T00:00:00.000Z"
  },
  {
    "id": "QT-1021",
    "opportunityId": "OPP-1021",
    "quoteNumber": "Q-1021",
    "owner": "Alex Morgan",
    "amount": 28038.114999284146,
    "status": "Approved",
    "createdAt": "2024-02-17T00:00:00.000Z"
  },
  {
    "id": "QT-1022",
    "opportunityId": "OPP-1022",
    "quoteNumber": "Q-1022",
    "owner": "Sofia Gomez",
    "amount": 46139.25182967377,
    "status": "Approved",
    "createdAt": "2024-09-29T00:00:00.000Z"
  },
  {
    "id": "QT-1023",
    "opportunityId": "OPP-1023",
    "quoteNumber": "Q-1023",
    "owner": "Sofia Gomez",
    "amount": 47145.3615242479,
    "status": "Approved",
    "createdAt": "2024-11-30T00:00:00.000Z"
  },
  {
    "id": "QT-1024",
    "opportunityId": "OPP-1024",
    "quoteNumber": "Q-1024",
    "owner": "Priya Patel",
    "amount": 94171.55351880618,
    "status": "Approved",
    "createdAt": "2024-05-22T00:00:00.000Z"
  },
  {
    "id": "QT-1025",
    "opportunityId": "OPP-1025",
    "quoteNumber": "Q-1025",
    "owner": "Priya Patel",
    "amount": 97109.08595559567,
    "status": "Approved",
    "createdAt": "2024-04-04T00:00:00.000Z"
  },
  {
    "id": "QT-1026",
    "opportunityId": "OPP-1026",
    "quoteNumber": "Q-1026",
    "owner": "Alex Morgan",
    "amount": 78382.9132817992,
    "status": "Approved",
    "createdAt": "2024-04-04T00:00:00.000Z"
  },
  {
    "id": "QT-1027",
    "opportunityId": "OPP-1027",
    "quoteNumber": "Q-1027",
    "owner": "Priya Patel",
    "amount": 15318.585945650548,
    "status": "Approved",
    "createdAt": "2025-01-06T00:00:00.000Z"
  },
  {
    "id": "QT-1028",
    "opportunityId": "OPP-1028",
    "quoteNumber": "Q-1028",
    "owner": "Alex Morgan",
    "amount": 31071.933331780074,
    "status": "Approved",
    "createdAt": "2024-06-10T00:00:00.000Z"
  },
  {
    "id": "QT-1029",
    "opportunityId": "OPP-1029",
    "quoteNumber": "Q-1029",
    "owner": "Jordan Smith",
    "amount": 16721.812922257755,
    "status": "Approved",
    "createdAt": "2024-11-12T00:00:00.000Z"
  },
  {
    "id": "QT-1030",
    "opportunityId": "OPP-1030",
    "quoteNumber": "Q-1030",
    "owner": "Priya Patel",
    "amount": 79145.6140209321,
    "status": "Approved",
    "createdAt": "2024-04-04T00:00:00.000Z"
  },
  {
    "id": "QT-1031",
    "opportunityId": "OPP-1031",
    "quoteNumber": "Q-1031",
    "owner": "Priya Patel",
    "amount": 38378.986242370665,
    "status": "Approved",
    "createdAt": "2024-04-06T00:00:00.000Z"
  },
  {
    "id": "QT-1032",
    "opportunityId": "OPP-1032",
    "quoteNumber": "Q-1032",
    "owner": "Jordan Smith",
    "amount": 65444.967587911495,
    "status": "Approved",
    "createdAt": "2024-10-02T00:00:00.000Z"
  },
  {
    "id": "QT-1033",
    "opportunityId": "OPP-1033",
    "quoteNumber": "Q-1033",
    "owner": "Jordan Smith",
    "amount": 39648.00774281659,
    "status": "Approved",
    "createdAt": "2024-05-19T00:00:00.000Z"
  },
  {
    "id": "QT-1034",
    "opportunityId": "OPP-1034",
    "quoteNumber": "Q-1034",
    "owner": "Priya Patel",
    "amount": 53366.63248163334,
    "status": "Approved",
    "createdAt": "2024-09-30T00:00:00.000Z"
  },
  {
    "id": "QT-1035",
    "opportunityId": "OPP-1035",
    "quoteNumber": "Q-1035",
    "owner": "Priya Patel",
    "amount": 83678.7560075603,
    "status": "Approved",
    "createdAt": "2024-11-24T00:00:00.000Z"
  },
  {
    "id": "QT-1036",
    "opportunityId": "OPP-1036",
    "quoteNumber": "Q-1036",
    "owner": "Priya Patel",
    "amount": 18590.41513519866,
    "status": "Approved",
    "createdAt": "2024-07-20T00:00:00.000Z"
  },
  {
    "id": "QT-1037",
    "opportunityId": "OPP-1037",
    "quoteNumber": "Q-1037",
    "owner": "Sofia Gomez",
    "amount": 94663.31699820078,
    "status": "Approved",
    "createdAt": "2024-11-05T00:00:00.000Z"
  },
  {
    "id": "QT-1038",
    "opportunityId": "OPP-1038",
    "quoteNumber": "Q-1038",
    "owner": "Sofia Gomez",
    "amount": 82883.71278823698,
    "status": "Approved",
    "createdAt": "2024-05-07T00:00:00.000Z"
  },
  {
    "id": "QT-1039",
    "opportunityId": "OPP-1039",
    "quoteNumber": "Q-1039",
    "owner": "Sofia Gomez",
    "amount": 101678.42061091532,
    "status": "Approved",
    "createdAt": "2024-09-06T00:00:00.000Z"
  },
  {
    "id": "QT-1040",
    "opportunityId": "OPP-1040",
    "quoteNumber": "Q-1040",
    "owner": "Jordan Smith",
    "amount": 86745.56239512334,
    "status": "Approved",
    "createdAt": "2025-01-02T00:00:00.000Z"
  },
  {
    "id": "QT-1041",
    "opportunityId": "OPP-1041",
    "quoteNumber": "Q-1041",
    "owner": "Sofia Gomez",
    "amount": 32288.173079051237,
    "status": "Approved",
    "createdAt": "2024-12-19T00:00:00.000Z"
  },
  {
    "id": "QT-1042",
    "opportunityId": "OPP-1042",
    "quoteNumber": "Q-1042",
    "owner": "Alex Morgan",
    "amount": 39805.653491183795,
    "status": "Approved",
    "createdAt": "2024-11-18T00:00:00.000Z"
  },
  {
    "id": "QT-1043",
    "opportunityId": "OPP-1043",
    "quoteNumber": "Q-1043",
    "owner": "Jordan Smith",
    "amount": 11207.116578702922,
    "status": "Approved",
    "createdAt": "2024-12-23T00:00:00.000Z"
  },
  {
    "id": "QT-1044",
    "opportunityId": "OPP-1044",
    "quoteNumber": "Q-1044",
    "owner": "Alex Morgan",
    "amount": 20144.009552941665,
    "status": "Approved",
    "createdAt": "2024-06-15T00:00:00.000Z"
  },
  {
    "id": "QT-1045",
    "opportunityId": "OPP-1045",
    "quoteNumber": "Q-1045",
    "owner": "Liam Chen",
    "amount": 39706.27959509034,
    "status": "Approved",
    "createdAt": "2024-09-30T00:00:00.000Z"
  },
  {
    "id": "QT-1046",
    "opportunityId": "OPP-1046",
    "quoteNumber": "Q-1046",
    "owner": "Jordan Smith",
    "amount": 35012.33693087691,
    "status": "Approved",
    "createdAt": "2024-05-03T00:00:00.000Z"
  },
  {
    "id": "QT-1047",
    "opportunityId": "OPP-1047",
    "quoteNumber": "Q-1047",
    "owner": "Sofia Gomez",
    "amount": 70520.02437843943,
    "status": "Approved",
    "createdAt": "2024-06-10T00:00:00.000Z"
  },
  {
    "id": "QT-1048",
    "opportunityId": "OPP-1048",
    "quoteNumber": "Q-1048",
    "owner": "Liam Chen",
    "amount": 24042.001676077023,
    "status": "Approved",
    "createdAt": "2024-07-28T00:00:00.000Z"
  },
  {
    "id": "QT-1049",
    "opportunityId": "OPP-1049",
    "quoteNumber": "Q-1049",
    "owner": "Sofia Gomez",
    "amount": 57097.01026810985,
    "status": "Approved",
    "createdAt": "2024-04-09T00:00:00.000Z"
  },
  {
    "id": "QT-1050",
    "opportunityId": "OPP-1050",
    "quoteNumber": "Q-1050",
    "owner": "Sofia Gomez",
    "amount": 43371.334430329814,
    "status": "Approved",
    "createdAt": "2024-09-05T00:00:00.000Z"
  },
  {
    "id": "QT-1051",
    "opportunityId": "OPP-1051",
    "quoteNumber": "Q-1051",
    "owner": "Liam Chen",
    "amount": 67304.35858352516,
    "status": "Approved",
    "createdAt": "2024-10-07T00:00:00.000Z"
  },
  {
    "id": "QT-1052",
    "opportunityId": "OPP-1052",
    "quoteNumber": "Q-1052",
    "owner": "Liam Chen",
    "amount": 91288.28246840116,
    "status": "Approved",
    "createdAt": "2024-04-07T00:00:00.000Z"
  },
  {
    "id": "QT-1053",
    "opportunityId": "OPP-1053",
    "quoteNumber": "Q-1053",
    "owner": "Priya Patel",
    "amount": 83084.33184825287,
    "status": "Approved",
    "createdAt": "2024-10-20T00:00:00.000Z"
  },
  {
    "id": "QT-1054",
    "opportunityId": "OPP-1054",
    "quoteNumber": "Q-1054",
    "owner": "Priya Patel",
    "amount": 44458.977469111764,
    "status": "Approved",
    "createdAt": "2024-05-27T00:00:00.000Z"
  },
  {
    "id": "QT-1055",
    "opportunityId": "OPP-1055",
    "quoteNumber": "Q-1055",
    "owner": "Priya Patel",
    "amount": 49070.128259239835,
    "status": "Approved",
    "createdAt": "2024-09-10T00:00:00.000Z"
  },
  {
    "id": "QT-1056",
    "opportunityId": "OPP-1056",
    "quoteNumber": "Q-1056",
    "owner": "Liam Chen",
    "amount": 84404.60065153857,
    "status": "Approved",
    "createdAt": "2024-01-12T00:00:00.000Z"
  },
  {
    "id": "QT-1057",
    "opportunityId": "OPP-1057",
    "quoteNumber": "Q-1057",
    "owner": "Alex Morgan",
    "amount": 13312.773781668184,
    "status": "Approved",
    "createdAt": "2024-03-17T00:00:00.000Z"
  },
  {
    "id": "QT-1058",
    "opportunityId": "OPP-1058",
    "quoteNumber": "Q-1058",
    "owner": "Priya Patel",
    "amount": 11252.261286724603,
    "status": "Approved",
    "createdAt": "2024-02-08T00:00:00.000Z"
  },
  {
    "id": "QT-1059",
    "opportunityId": "OPP-1059",
    "quoteNumber": "Q-1059",
    "owner": "Sofia Gomez",
    "amount": 27268.867027916822,
    "status": "Approved",
    "createdAt": "2024-07-22T00:00:00.000Z"
  },
  {
    "id": "QT-1060",
    "opportunityId": "OPP-1060",
    "quoteNumber": "Q-1060",
    "owner": "Sofia Gomez",
    "amount": 75037.78383083435,
    "status": "Approved",
    "createdAt": "2024-05-02T00:00:00.000Z"
  }
]